hyperSel/__init__.py
hyperSel/classifier.py
hyperSel/compiler.py
hyperSel/config.py
hyperSel/db.py
hyperSel/graph.py
hyperSel/instance.py
hyperSel/log.py
hyperSel/mobile_instance.py
hyperSel/notifications.py
hyperSel/parser.py
hyperSel/req.py
hyperSel/test_internal_tor.py
hyperSel/test_zillow.py
hyperSel/tor_chrome_util.py
hyperSel/util.py
hypersel-7.32.dist-info/METADATA
hypersel-7.32.dist-info/WHEEL
hypersel-7.32.dist-info/top_level.txt
hypersel-7.32.dist-info/RECORD
