Metadata-Version: 2.1
Name: hypersel
Version: 7.32
Summary: A Python-based web automation and data scraping framework
Home-page: https://github.com/foreandr/hyperSel
Author: foreandr
Author-email: foreandr@gmail.com
License: UNKNOWN
Platform: UNKNOWN
Classifier: Programming Language :: Python :: 3
Classifier: License :: OSI Approved :: MIT License
Classifier: Operating System :: OS Independent
Requires-Python: >=3.6
Requires-Dist: selenium
Requires-Dist: beautifulsoup4
Requires-Dist: webdriver-manager
Requires-Dist: lxml
Requires-Dist: requests
Requires-Dist: nodriver
Requires-Dist: psutil
Requires-Dist: playwright
Requires-Dist: undetected-playwright
Requires-Dist: screeninfo
Requires-Dist: customtkinter
Requires-Dist: pillow
Requires-Dist: pyinstaller
Requires-Dist: networkx
Requires-Dist: pyvis
Requires-Dist: html5lib
Requires-Dist: stem
Requires-Dist: wheel
Requires-Dist: undetected-chromedriver
